geosoftdesign/__init__.py
geosoftdesign/common.py
geosoftdesign/geosoftdesign.py
geosoftdesign-0.0.1.dist-info/AUTHORS.rst
geosoftdesign-0.0.1.dist-info/LICENSE
geosoftdesign-0.0.1.dist-info/METADATA
geosoftdesign-0.0.1.dist-info/WHEEL
geosoftdesign-0.0.1.dist-info/entry_points.txt
geosoftdesign-0.0.1.dist-info/top_level.txt
geosoftdesign-0.0.1.dist-info/RECORD
